[
  {
    "term": "ハンサム",
    "frequency": 900,
    "example_en": "He is a handsome man.",
    "example_ru": "Он красивый мужчина.",
    "meaning_en": "handsome",
    "meaning_ru": "красивый (о мужчине)",
    "transcription": "ハンサム",
    "example_native": "彼はハンサムな男です。",
    "term_with_transcription": "ハンサム",
    "example_with_transcription": "彼[かれ]はハンサムな男[おとこ]です。",
    "audio_word": "https://assets.peatch.io/audio/japanese/word_ENVuZZfWhb.m4a",
    "audio_example": "https://assets.peatch.io/audio/japanese/example_ugEKjZO-Kp.m4a"
  },
  {
    "term": "きれい",
    "frequency": 250,
    "example_en": "The room is clean and beautiful.",
    "example_ru": "Комната чистая и красивая.",
    "meaning_en": "beautiful, clean",
    "meaning_ru": "красивый, чистый",
    "transcription": "きれい",
    "example_native": "部屋はきれいです。",
    "term_with_transcription": "きれい",
    "example_with_transcription": "部屋[へや]はきれいです。",
    "audio_word": "https://assets.peatch.io/audio/japanese/word_YwKje_zieg.m4a",
    "audio_example": "https://assets.peatch.io/audio/japanese/example_SeARRMiZVk.m4a"
  },
  {
    "term": "静か",
    "frequency": 400,
    "example_en": "This park is quiet.",
    "example_ru": "Этот парк тихий.",
    "meaning_en": "quiet",
    "meaning_ru": "тихий",
    "transcription": "しずか",
    "example_native": "この公園は静かです。",
    "term_with_transcription": "静か[しずか]",
    "example_with_transcription": "この公園[こうえん]は静か[しずか]です。",
    "audio_word": "https://assets.peatch.io/audio/japanese/word_xN4hmvECbX.m4a",
    "audio_example": "https://assets.peatch.io/audio/japanese/example_iPSTB4JbJF.m4a"
  },
  {
    "term": "賑やか",
    "frequency": 650,
    "example_en": "The festival is lively.",
    "example_ru": "Фестиваль оживлённый.",
    "meaning_en": "lively",
    "meaning_ru": "оживлённый",
    "transcription": "にぎやか",
    "example_native": "祭りは賑やかです。",
    "term_with_transcription": "賑やか[にぎやか]",
    "example_with_transcription": "祭[まつ]りは賑やか[にぎやか]です。",
    "audio_word": "https://assets.peatch.io/audio/japanese/word_ltPfKjfIZM.m4a",
    "audio_example": "https://assets.peatch.io/audio/japanese/example_SE610G3q1q.m4a"
  },
  {
    "term": "有名",
    "frequency": 320,
    "example_en": "Kyoto is a famous city.",
    "example_ru": "Киото — знаменитый город.",
    "meaning_en": "famous",
    "meaning_ru": "знаменитый",
    "transcription": "ゆうめい",
    "example_native": "京都は有名な町です。",
    "term_with_transcription": "有名[ゆうめい]",
    "example_with_transcription": "京都[きょうと]は有名[ゆうめい]な町[まち]です。",
    "audio_word": "https://assets.peatch.io/audio/japanese/word_XlUf9-rnXY.m4a",
    "audio_example": "https://assets.peatch.io/audio/japanese/example_4IY2JeeAjC.m4a"
  },
  {
    "term": "親切",
    "frequency": 350,
    "example_en": "She is kind to everyone.",
    "example_ru": "Она добра ко всем.",
    "meaning_en": "kind",
    "meaning_ru": "добрый",
    "transcription": "しんせつ",
    "example_native": "彼女は親切な人です。",
    "term_with_transcription": "親切[しんせつ]",
    "example_with_transcription": "彼女[かのじょ]は親切[しんせつ]な人[ひと]です。",
    "audio_word": "https://assets.peatch.io/audio/japanese/word_OizGzMiF2j.m4a",
    "audio_example": "https://assets.peatch.io/audio/japanese/example_7nimyb_6Ma.m4a"
  },
  {
    "term": "元気",
    "frequency": 180,
    "example_en": "He is cheerful every day.",
    "example_ru": "Он каждый день бодр.",
    "meaning_en": "healthy, cheerful",
    "meaning_ru": "здоровый, бодрый",
    "transcription": "げんき",
    "example_native": "彼はいつも元気です。",
    "term_with_transcription": "元気[げんき]",
    "example_with_transcription": "彼[かれ]はいつも元気[げんき]です。",
    "audio_word": "https://assets.peatch.io/audio/japanese/word_BiLUMORfWa.m4a",
    "audio_example": "https://assets.peatch.io/audio/japanese/example_ZeMMKNot-X.m4a"
  },
  {
    "term": "暇",
    "frequency": 500,
    "example_en": "I am free on Sunday.",
    "example_ru": "Я свободен в воскресенье.",
    "meaning_en": "free (time)",
    "meaning_ru": "свободный (о времени)",
    "transcription": "ひま",
    "example_native": "日曜日は暇です。",
    "term_with_transcription": "暇[ひま]",
    "example_with_transcription": "日曜日[にちようび]は暇[ひま]です。",
    "audio_word": "https://assets.peatch.io/audio/japanese/word_9wRxZUVsSH.m4a",
    "audio_example": "https://assets.peatch.io/audio/japanese/example_8VjRTPh7Xw.m4a"
  },
  {
    "term": "便利",
    "frequency": 240,
    "example_en": "This app is convenient.",
    "example_ru": "Это приложение удобно.",
    "meaning_en": "convenient",
    "meaning_ru": "удобный",
    "transcription": "べんり",
    "example_native": "このアプリは便利です。",
    "term_with_transcription": "便利[べんり]",
    "example_with_transcription": "このアプリは便利[べんり]です。",
    "audio_word": "https://assets.peatch.io/audio/japanese/word_Si0yReZ9wG.m4a",
    "audio_example": "https://assets.peatch.io/audio/japanese/example_P5RnjSzlPW.m4a"
  },
  {
    "term": "素敵",
    "frequency": 420,
    "example_en": "It's a wonderful dress.",
    "example_ru": "Это прекрасное платье.",
    "meaning_en": "fine, nice, wonderful",
    "meaning_ru": "прекрасный, замечательный",
    "transcription": "すてき",
    "example_native": "素敵なドレスですね。",
    "term_with_transcription": "素敵[すてき]",
    "example_with_transcription": "素敵[すてき]なドレスですね。",
    "audio_word": "https://assets.peatch.io/audio/japanese/word_Iw2_n6k77Q.m4a",
    "audio_example": "https://assets.peatch.io/audio/japanese/example_ZU7wtwRtht.m4a"
  },
  {
    "term": "大きい",
    "frequency": 120,
    "example_en": "That house is big.",
    "example_ru": "Тот дом большой.",
    "meaning_en": "big, large",
    "meaning_ru": "большой",
    "transcription": "おおきい",
    "example_native": "あの家は大きいです。",
    "term_with_transcription": "大きい[おおきい]",
    "example_with_transcription": "あの家[いえ]は大きい[おおきい]です。",
    "audio_word": "https://assets.peatch.io/audio/japanese/word_HQmtD7ruhO.m4a",
    "audio_example": "https://assets.peatch.io/audio/japanese/example_xzKclVoPdK.m4a"
  },
  {
    "term": "小さい",
    "frequency": 150,
    "example_en": "My bag is small.",
    "example_ru": "Моя сумка маленькая.",
    "meaning_en": "small, little",
    "meaning_ru": "маленький",
    "transcription": "ちいさい",
    "example_native": "私のかばんは小さいです。",
    "term_with_transcription": "小さい[ちいさい]",
    "example_with_transcription": "私[わたし]のかばんは小さい[ちいさい]です。",
    "audio_word": "https://assets.peatch.io/audio/japanese/word_FFLIpiKWBJ.m4a",
    "audio_example": "https://assets.peatch.io/audio/japanese/example_j-NhZPKuxg.m4a"
  },
  {
    "term": "新しい",
    "frequency": 140,
    "example_en": "I bought a new phone.",
    "example_ru": "Я купил новый телефон.",
    "meaning_en": "new",
    "meaning_ru": "новый",
    "transcription": "あたらしい",
    "example_native": "新しい携帯を買いました。",
    "term_with_transcription": "新しい[あたらしい]",
    "example_with_transcription": "新しい[あたらしい]携帯[けいたい]を買[か]いました。",
    "audio_word": "https://assets.peatch.io/audio/japanese/word_SlwZZXU3De.m4a",
    "audio_example": "https://assets.peatch.io/audio/japanese/example_BvqUjdh97s.m4a"
  },
  {
    "term": "古い",
    "frequency": 210,
    "example_en": "This building is old.",
    "example_ru": "Это здание старое.",
    "meaning_en": "old (not of age)",
    "meaning_ru": "старый (не о возрасте)",
    "transcription": "ふるい",
    "example_native": "この建物は古いです。",
    "term_with_transcription": "古い[ふるい]",
    "example_with_transcription": "この建物[たてもの]は古い[ふるい]です。",
    "audio_word": "https://assets.peatch.io/audio/japanese/word_RC6FOPtipx.m4a",
    "audio_example": "https://assets.peatch.io/audio/japanese/example_H1ufOTe4lx.m4a"
  },
  {
    "term": "いい",
    "frequency": 60,
    "example_en": "This book is good.",
    "example_ru": "Эта книга хорошая.",
    "meaning_en": "good",
    "meaning_ru": "хороший",
    "transcription": "いい",
    "example_native": "この本はいいです。",
    "term_with_transcription": "いい",
    "example_with_transcription": "この本[ほん]はいいです。",
    "audio_word": "https://assets.peatch.io/audio/japanese/word_jSOshkkA0D.m4a",
    "audio_example": "https://assets.peatch.io/audio/japanese/example_IRN2T_6COE.m4a"
  },
  {
    "term": "悪い",
    "frequency": 230,
    "example_en": "That is a bad idea.",
    "example_ru": "Это плохая идея.",
    "meaning_en": "bad",
    "meaning_ru": "плохой",
    "transcription": "わるい",
    "example_native": "それは悪い考えです。",
    "term_with_transcription": "悪い[わるい]",
    "example_with_transcription": "それは悪い[わるい]考[かんが]えです。",
    "audio_word": "https://assets.peatch.io/audio/japanese/word_myhfCsfCad.m4a",
    "audio_example": "https://assets.peatch.io/audio/japanese/example_yp0Jwy0dJ-.m4a"
  },
  {
    "term": "厚い",
    "frequency": 800,
    "example_en": "This book is thick.",
    "example_ru": "Эта книга толстая.",
    "meaning_en": "thick",
    "meaning_ru": "толстый",
    "transcription": "あつい",
    "example_native": "この本は厚いです。",
    "term_with_transcription": "厚い[あつい]",
    "example_with_transcription": "この本[ほん]は厚い[あつい]です。",
    "audio_word": "https://assets.peatch.io/audio/japanese/word_jutvATasbI.m4a",
    "audio_example": "https://assets.peatch.io/audio/japanese/example_rHn8lQeNNj.m4a"
  },
  {
    "term": "熱い",
    "frequency": 350,
    "example_en": "The tea is hot.",
    "example_ru": "Чай горячий.",
    "meaning_en": "hot",
    "meaning_ru": "горячий",
    "transcription": "あつい",
    "example_native": "お茶は熱いです。",
    "term_with_transcription": "熱い[あつい]",
    "example_with_transcription": "お茶[ちゃ]は熱い[あつい]です。",
    "audio_word": "https://assets.peatch.io/audio/japanese/word_fQQsq_FOz0.m4a",
    "audio_example": "https://assets.peatch.io/audio/japanese/example_bTaoOCQaIZ.m4a"
  },
  {
    "term": "寒い",
    "frequency": 210,
    "example_en": "It is cold today.",
    "example_ru": "Сегодня холодно.",
    "meaning_en": "cold (temperature)",
    "meaning_ru": "холодный (о погоде)",
    "transcription": "さむい",
    "example_native": "今日は寒いです。",
    "term_with_transcription": "寒い[さむい]",
    "example_with_transcription": "今日[きょう]は寒い[さむい]です。",
    "audio_word": "https://assets.peatch.io/audio/japanese/word_1RdyOoYM8L.m4a",
    "audio_example": "https://assets.peatch.io/audio/japanese/example_w6eZ1vRcUz.m4a"
  },
  {
    "term": "冷たい",
    "frequency": 280,
    "example_en": "The water is cold.",
    "example_ru": "Вода холодная.",
    "meaning_en": "cold (touch)",
    "meaning_ru": "холодный (на ощупь)",
    "transcription": "つめたい",
    "example_native": "水は冷たいです。",
    "term_with_transcription": "冷たい[つめたい]",
    "example_with_transcription": "水[みず]は冷たい[つめたい]です。",
    "audio_word": "https://assets.peatch.io/audio/japanese/word_Ky5XtuCDcp.m4a",
    "audio_example": "https://assets.peatch.io/audio/japanese/example_zRcyHp2j0z.m4a"
  },
  {
    "term": "難しい",
    "frequency": 300,
    "example_en": "This problem is difficult.",
    "example_ru": "Эта задача сложная.",
    "meaning_en": "difficult",
    "meaning_ru": "сложный",
    "transcription": "むずかしい",
    "example_native": "この問題は難しいです。",
    "term_with_transcription": "難しい[むずかしい]",
    "example_with_transcription": "この問題[もんだい]は難しい[むずかしい]です。",
    "audio_word": "https://assets.peatch.io/audio/japanese/word_pNZfUeNZsi.m4a",
    "audio_example": "https://assets.peatch.io/audio/japanese/example_PEmT1Cm_hn.m4a"
  },
  {
    "term": "易しい",
    "frequency": 380,
    "example_en": "This question is easy.",
    "example_ru": "Этот вопрос легкий.",
    "meaning_en": "easy",
    "meaning_ru": "лёгкий",
    "transcription": "やさしい",
    "example_native": "この質問は易しいです。",
    "term_with_transcription": "易しい[やさしい]",
    "example_with_transcription": "この質問[しつもん]は易しい[やさしい]です。",
    "audio_word": "https://assets.peatch.io/audio/japanese/word_swPloS7m7O.m4a",
    "audio_example": "https://assets.peatch.io/audio/japanese/example_OvnbxFhg-d.m4a"
  },
  {
    "term": "高い",
    "frequency": 160,
    "example_en": "This car is expensive.",
    "example_ru": "Эта машина дорогая.",
    "meaning_en": "expensive, tall, high",
    "meaning_ru": "дорогой, высокий",
    "transcription": "たかい",
    "example_native": "この車は高いです。",
    "term_with_transcription": "高い[たかい]",
    "example_with_transcription": "この車[くるま]は高い[たかい]です。",
    "audio_word": "https://assets.peatch.io/audio/japanese/word_2GJmtlXiiC.m4a",
    "audio_example": "https://assets.peatch.io/audio/japanese/example_rnzUH7MYHQ.m4a"
  },
  {
    "term": "安い",
    "frequency": 170,
    "example_en": "This bag is inexpensive.",
    "example_ru": "Эта сумка недорогая.",
    "meaning_en": "inexpensive",
    "meaning_ru": "недорогой",
    "transcription": "やすい",
    "example_native": "このかばんは安いです。",
    "term_with_transcription": "安い[やすい]",
    "example_with_transcription": "このかばんは安い[やすい]です。",
    "audio_word": "https://assets.peatch.io/audio/japanese/word_kv8_P8fnnr.m4a",
    "audio_example": "https://assets.peatch.io/audio/japanese/example_MfHpKAOONB.m4a"
  },
  {
    "term": "低い",
    "frequency": 420,
    "example_en": "This chair is low.",
    "example_ru": "Этот стул низкий.",
    "meaning_en": "low",
    "meaning_ru": "низкий",
    "transcription": "ひくい",
    "example_native": "この椅子は低いです。",
    "term_with_transcription": "低い[ひくい]",
    "example_with_transcription": "この椅子[いす]は低い[ひくい]です。",
    "audio_word": "https://assets.peatch.io/audio/japanese/word_i8JofJYRmv.m4a",
    "audio_example": "https://assets.peatch.io/audio/japanese/example_6jDlnSYamM.m4a"
  },
  {
    "term": "面白い",
    "frequency": 200,
    "example_en": "This movie is interesting.",
    "example_ru": "Этот фильм интересный.",
    "meaning_en": "interesting",
    "meaning_ru": "интересный",
    "transcription": "おもしろい",
    "example_native": "この映画は面白いです。",
    "term_with_transcription": "面白い[おもしろい]",
    "example_with_transcription": "この映画[えいが]は面白い[おもしろい]です。",
    "audio_word": "https://assets.peatch.io/audio/japanese/word_kMG8hM4jwO.m4a",
    "audio_example": "https://assets.peatch.io/audio/japanese/example_eRYwfYmSWy.m4a"
  },
  {
    "term": "美味しい",
    "frequency": 100,
    "example_en": "This cake is delicious.",
    "example_ru": "Этот торт вкусный.",
    "meaning_en": "delicious, tasty",
    "meaning_ru": "вкусный",
    "transcription": "おいしい",
    "example_native": "このケーキは美味しいです。",
    "term_with_transcription": "美味しい[おいしい]",
    "example_with_transcription": "このケーキは美味しい[おいしい]です。",
    "audio_word": "https://assets.peatch.io/audio/japanese/word_PjDkg1QGJQ.m4a",
    "audio_example": "https://assets.peatch.io/audio/japanese/example_kPl1zUZACz.m4a"
  },
  {
    "term": "忙しい",
    "frequency": 130,
    "example_en": "I am busy this week.",
    "example_ru": "Я занят на этой неделе.",
    "meaning_en": "busy",
    "meaning_ru": "занятой",
    "transcription": "いそがしい",
    "example_native": "今週は忙しいです。",
    "term_with_transcription": "忙しい[いそがしい]",
    "example_with_transcription": "今週[こんしゅう]は忙しい[いそがしい]です。",
    "audio_word": "https://assets.peatch.io/audio/japanese/word_IW6CPE10ES.m4a",
    "audio_example": "https://assets.peatch.io/audio/japanese/example_1djdPQJ1OA.m4a"
  },
  {
    "term": "楽しい",
    "frequency": 170,
    "example_en": "The party was enjoyable.",
    "example_ru": "Вечеринка была весёлой.",
    "meaning_en": "enjoyable",
    "meaning_ru": "весёлый, приятный",
    "transcription": "たのしい",
    "example_native": "パーティーは楽しかったです。",
    "term_with_transcription": "楽しい[たのしい]",
    "example_with_transcription": "パーティーは楽しい[たのしい]かったです。",
    "audio_word": "https://assets.peatch.io/audio/japanese/word_fKUbb6s4Tl.m4a",
    "audio_example": "https://assets.peatch.io/audio/japanese/example_xWVkalO0cY.m4a"
  },
  {
    "term": "白い",
    "frequency": 210,
    "example_en": "The cat is white.",
    "example_ru": "Кошка белая.",
    "meaning_en": "white",
    "meaning_ru": "белый",
    "transcription": "しろい",
    "example_native": "猫は白いです。",
    "term_with_transcription": "白い[しろい]",
    "example_with_transcription": "猫[ねこ]は白い[しろい]です。",
    "audio_word": "https://assets.peatch.io/audio/japanese/word_4CB2Qotztx.m4a",
    "audio_example": "https://assets.peatch.io/audio/japanese/example_uW4xMQwldH.m4a"
  },
  {
    "term": "黒い",
    "frequency": 220,
    "example_en": "He has black hair.",
    "example_ru": "У него чёрные волосы.",
    "meaning_en": "black",
    "meaning_ru": "чёрный",
    "transcription": "くろい",
    "example_native": "彼は黒い髪です。",
    "term_with_transcription": "黒い[くろい]",
    "example_with_transcription": "彼[かれ]は黒い[くろい]髪[かみ]です。",
    "audio_word": "https://assets.peatch.io/audio/japanese/word_DUIZORnmEb.m4a",
    "audio_example": "https://assets.peatch.io/audio/japanese/example_gTo_T5bLVZ.m4a"
  },
  {
    "term": "赤い",
    "frequency": 230,
    "example_en": "The apple is red.",
    "example_ru": "Яблоко красное.",
    "meaning_en": "red",
    "meaning_ru": "красный",
    "transcription": "あかい",
    "example_native": "りんごは赤いです。",
    "term_with_transcription": "赤い[あかい]",
    "example_with_transcription": "りんごは赤い[あかい]です。",
    "audio_word": "https://assets.peatch.io/audio/japanese/word_CrepS5KT5C.m4a",
    "audio_example": "https://assets.peatch.io/audio/japanese/example_kV651fCOFI.m4a"
  },
  {
    "term": "青い",
    "frequency": 240,
    "example_en": "The sky is blue.",
    "example_ru": "Небо голубое.",
    "meaning_en": "blue",
    "meaning_ru": "голубой, синий",
    "transcription": "あおい",
    "example_native": "空は青いです。",
    "term_with_transcription": "青い[あおい]",
    "example_with_transcription": "空[そら]は青い[あおい]です。",
    "audio_word": "https://assets.peatch.io/audio/japanese/word_1k7oFksv_d.m4a",
    "audio_example": "https://assets.peatch.io/audio/japanese/example_2mQZLbZt8x.m4a"
  },
  {
    "term": "桜",
    "frequency": 320,
    "example_en": "Cherry blossoms are beautiful.",
    "example_ru": "Цветы сакуры красивые.",
    "meaning_en": "cherry (blossom)",
    "meaning_ru": "сакура",
    "transcription": "さくら",
    "example_native": "桜が咲きました。",
    "term_with_transcription": "桜[さくら]",
    "example_with_transcription": "桜[さくら]が咲[さ]きました。",
    "audio_word": "https://assets.peatch.io/audio/japanese/word_tLTmYdTC-d.m4a",
    "audio_example": "https://assets.peatch.io/audio/japanese/example_pGZlwc0Zid.m4a"
  },
  {
    "term": "山",
    "frequency": 100,
    "example_en": "There is a mountain over there.",
    "example_ru": "Вон там гора.",
    "meaning_en": "mountain",
    "meaning_ru": "гора",
    "transcription": "やま",
    "example_native": "あそこに山があります。",
    "term_with_transcription": "山[やま]",
    "example_with_transcription": "あそこに山[やま]があります。",
    "audio_word": "https://assets.peatch.io/audio/japanese/word_3nz64lHfbL.m4a",
    "audio_example": "https://assets.peatch.io/audio/japanese/example_foRBbhhyq_.m4a"
  },
  {
    "term": "町",
    "frequency": 140,
    "example_en": "This town is quiet.",
    "example_ru": "Этот город тихий.",
    "meaning_en": "town, city",
    "meaning_ru": "город, городок",
    "transcription": "まち",
    "example_native": "この町は静かです。",
    "term_with_transcription": "町[まち]",
    "example_with_transcription": "この町[まち]は静か[しずか]です。",
    "audio_word": "https://assets.peatch.io/audio/japanese/word_XTG5k7AOQ5.m4a",
    "audio_example": "https://assets.peatch.io/audio/japanese/example_0UJyEALqQ5.m4a"
  },
  {
    "term": "食べ物",
    "frequency": 110,
    "example_en": "What food do you like?",
    "example_ru": "Какую еду ты любишь?",
    "meaning_en": "food",
    "meaning_ru": "еда",
    "transcription": "たべもの",
    "example_native": "好きな食べ物は何ですか？",
    "term_with_transcription": "食べ物[たべもの]",
    "example_with_transcription": "好[す]きな食べ物[たべもの]は何[なに]ですか？",
    "audio_word": "https://assets.peatch.io/audio/japanese/word_lgsTSGQQ9C.m4a",
    "audio_example": "https://assets.peatch.io/audio/japanese/example_XhotpjyBFJ.m4a"
  },
  {
    "term": "車",
    "frequency": 80,
    "example_en": "I have a car.",
    "example_ru": "У меня есть машина.",
    "meaning_en": "car, vehicle",
    "meaning_ru": "машина, автомобиль",
    "transcription": "くるま",
    "example_native": "私は車を持っています。",
    "term_with_transcription": "車[くるま]",
    "example_with_transcription": "私[わたし]は車[くるま]を持[も]っています。",
    "audio_word": "https://assets.peatch.io/audio/japanese/word_5xpsRsDKYk.m4a",
    "audio_example": "https://assets.peatch.io/audio/japanese/example_aEVmRRy818.m4a"
  },
  {
    "term": "所",
    "frequency": 260,
    "example_en": "This is a quiet place.",
    "example_ru": "Это тихое место.",
    "meaning_en": "place",
    "meaning_ru": "место",
    "transcription": "ところ",
    "example_native": "ここは静かな所です。",
    "term_with_transcription": "所[ところ]",
    "example_with_transcription": "ここは静[しず]かな所[ところ]です。",
    "audio_word": "https://assets.peatch.io/audio/japanese/word_TaIsHyYNtH.m4a",
    "audio_example": "https://assets.peatch.io/audio/japanese/example_UNJAz9t75p.m4a"
  },
  {
    "term": "寮",
    "frequency": 700,
    "example_en": "I live in a dormitory.",
    "example_ru": "Я живу в общежитии.",
    "meaning_en": "dormitory",
    "meaning_ru": "общежитие",
    "transcription": "りょう",
    "example_native": "私は寮に住んでいます。",
    "term_with_transcription": "寮[りょう]",
    "example_with_transcription": "私[わたし]は寮[りょう]に住[す]んでいます。",
    "audio_word": "https://assets.peatch.io/audio/japanese/word_YYrMhPvuvO.m4a",
    "audio_example": "https://assets.peatch.io/audio/japanese/example_nY_7j7kaav.m4a"
  },
  {
    "term": "勉強",
    "frequency": 90,
    "example_en": "I study Japanese every day.",
    "example_ru": "Я учу японский каждый день.",
    "meaning_en": "study",
    "meaning_ru": "учёба, учиться",
    "transcription": "べんきょう",
    "example_native": "毎日日本語を勉強します。",
    "term_with_transcription": "勉強[べんきょう]",
    "example_with_transcription": "毎日[まいにち]日本語[にほんご]を勉強[べんきょう]します。",
    "audio_word": "https://assets.peatch.io/audio/japanese/word_XaPJ1tR8lu.m4a",
    "audio_example": "https://assets.peatch.io/audio/japanese/example_lrsB1tMSob.m4a"
  },
  {
    "term": "生活",
    "frequency": 260,
    "example_en": "Life in Japan is interesting.",
    "example_ru": "Жизнь в Японии интересная.",
    "meaning_en": "life",
    "meaning_ru": "жизнь, быт",
    "transcription": "せいかつ",
    "example_native": "日本の生活は面白いです。",
    "term_with_transcription": "生活[せいかつ]",
    "example_with_transcription": "日本[にほん]の生活[せいかつ]は面白い[おもしろい]です。",
    "audio_word": "https://assets.peatch.io/audio/japanese/word_XZVo7YeXzR.m4a",
    "audio_example": "https://assets.peatch.io/audio/japanese/example_kZN2xbEs8y.m4a"
  },
  {
    "term": "お仕事",
    "frequency": 150,
    "example_en": "What is your job?",
    "example_ru": "Какая у вас работа?",
    "meaning_en": "work, job (polite)",
    "meaning_ru": "работа (вежливо)",
    "transcription": "おしごと",
    "example_native": "お仕事は何ですか？",
    "term_with_transcription": "お仕事[おしごと]",
    "example_with_transcription": "お仕事[おしごと]は何[なん]ですか？",
    "audio_word": "https://assets.peatch.io/audio/japanese/word_dtDRaaqGLa.m4a",
    "audio_example": "https://assets.peatch.io/audio/japanese/example_ZHSEiS5hHa.m4a"
  },
  {
    "term": "どう",
    "frequency": 100,
    "example_en": "How is this?",
    "example_ru": "Как это?",
    "meaning_en": "how",
    "meaning_ru": "как",
    "transcription": "どう",
    "example_native": "これはどうですか？",
    "term_with_transcription": "どう",
    "example_with_transcription": "これはどうですか？",
    "audio_word": "https://assets.peatch.io/audio/japanese/word_KuVYvStlja.m4a",
    "audio_example": "https://assets.peatch.io/audio/japanese/example_lrT8-iHfbG.m4a"
  },
  {
    "term": "どんな",
    "frequency": 130,
    "example_en": "What kind of music do you like?",
    "example_ru": "Какую музыку ты любишь?",
    "meaning_en": "what kind of",
    "meaning_ru": "какой, какого рода",
    "transcription": "どんな",
    "example_native": "どんな音楽が好きですか？",
    "term_with_transcription": "どんな",
    "example_with_transcription": "どんな音楽[おんがく]が好[す]きですか？",
    "audio_word": "https://assets.peatch.io/audio/japanese/word_xTqiNnWQdQ.m4a",
    "audio_example": "https://assets.peatch.io/audio/japanese/example_gom2dCpge8.m4a"
  },
  {
    "term": "どれ",
    "frequency": 160,
    "example_en": "Which one is your bag?",
    "example_ru": "Которая твоя сумка?",
    "meaning_en": "which (one of three or more)",
    "meaning_ru": "который (из трёх и более)",
    "transcription": "どれ",
    "example_native": "どれがあなたのかばんですか？",
    "term_with_transcription": "どれ",
    "example_with_transcription": "どれがあなたのかばんですか？",
    "audio_word": "https://assets.peatch.io/audio/japanese/word_uW2RfauA_P.m4a",
    "audio_example": "https://assets.peatch.io/audio/japanese/example_a8V3-Ktuwo.m4a"
  },
  {
    "term": "とても",
    "frequency": 70,
    "example_en": "This cake is very delicious.",
    "example_ru": "Этот торт очень вкусный.",
    "meaning_en": "very",
    "meaning_ru": "очень",
    "transcription": "とても",
    "example_native": "このケーキはとても美味しいです。",
    "term_with_transcription": "とても",
    "example_with_transcription": "このケーキはとても美味しい[おいしい]です。",
    "audio_word": "https://assets.peatch.io/audio/japanese/word_kbMFdYmhJ1.m4a",
    "audio_example": "https://assets.peatch.io/audio/japanese/example_vRDjucMURt.m4a"
  },
  {
    "term": "あまり",
    "frequency": 180,
    "example_en": "I don't eat much meat.",
    "example_ru": "Я не ем много мяса.",
    "meaning_en": "not so (used with negatives)",
    "meaning_ru": "не очень (с отрицаниями)",
    "transcription": "あまり",
    "example_native": "私はあまり肉を食べません。",
    "term_with_transcription": "あまり",
    "example_with_transcription": "私[わたし]はあまり肉[にく]を食[た]べません。",
    "audio_word": "https://assets.peatch.io/audio/japanese/word_NVAFnIVBni.m4a",
    "audio_example": "https://assets.peatch.io/audio/japanese/example_Tfz1FUryvk.m4a"
  },
  {
    "term": "そして",
    "frequency": 100,
    "example_en": "I went to the library and then to the café.",
    "example_ru": "Я пошёл в библиотеку, а потом в кафе.",
    "meaning_en": "and (to connect sentences)",
    "meaning_ru": "и (для соединения предложений)",
    "transcription": "そして",
    "example_native": "図書館に行きました。そして、カフェにも行きました。",
    "term_with_transcription": "そして",
    "example_with_transcription": "図書館[としょかん]に行[い]きました。そして、カフェにも行[い]きました。",
    "audio_word": "https://assets.peatch.io/audio/japanese/word_jpP7Cuq0k3.m4a",
    "audio_example": "https://assets.peatch.io/audio/japanese/example_IK_oH9-gA7.m4a"
  },
  {
    "term": "お元気ですか",
    "frequency": 110,
    "example_en": "How are you?",
    "example_ru": "Как вы?",
    "meaning_en": "How are you?",
    "meaning_ru": "Как дела?",
    "transcription": "おげんきですか",
    "example_native": "こんにちは。お元気ですか？",
    "term_with_transcription": "お元気[げんき]ですか",
    "example_with_transcription": "こんにちは。お元気[げんき]ですか？",
    "audio_word": "https://assets.peatch.io/audio/japanese/word_4mUQoPdOIQ.m4a",
    "audio_example": "https://assets.peatch.io/audio/japanese/example_kZoBrD3aQZ.m4a"
  },
  {
    "term": "そうですね",
    "frequency": 120,
    "example_en": "Well, let me see.",
    "example_ru": "Ну, дайте подумать.",
    "meaning_en": "Well, let me see. (pausing)",
    "meaning_ru": "Ну, дайте подумать. (пауза)",
    "transcription": "そうですね",
    "example_native": "そうですね、難しい質問ですね。",
    "term_with_transcription": "そうですね",
    "example_with_transcription": "そうですね、難しい[むずかしい]質問[しつもん]ですね。",
    "audio_word": "https://assets.peatch.io/audio/japanese/word_mORJJsEV6G.m4a",
    "audio_example": "https://assets.peatch.io/audio/japanese/example_tmOyvhPnOS.m4a"
  },
  {
    "term": "日本の生活に慣れましたか",
    "frequency": 500,
    "example_en": "Have you got used to the life in Japan?",
    "example_ru": "Вы привыкли к жизни в Японии?",
    "meaning_en": "Have you got used to the life in Japan?",
    "meaning_ru": "Вы привыкли к жизни в Японии?",
    "transcription": "にほんのせいかつになれましたか",
    "example_native": "日本の生活に慣れましたか？",
    "term_with_transcription": "日本[にほん]の生活[せいかつ]に慣[な]れましたか",
    "example_with_transcription": "日本[にほん]の生活[せいかつ]に慣[な]れましたか？",
    "audio_word": "https://assets.peatch.io/audio/japanese/word_w7YjdPGxSV.m4a",
    "audio_example": "https://assets.peatch.io/audio/japanese/example_hE4JTrt_RU.m4a"
  },
  {
    "term": "もう一杯いかがですか",
    "frequency": 700,
    "example_en": "Won't you have another cup?",
    "example_ru": "Не хотите ещё одну чашку?",
    "meaning_en": "Won't you have another cup?",
    "meaning_ru": "Не хотите ещё одну чашку?",
    "transcription": "もういっぱいいかがですか",
    "example_native": "コーヒーをもう一杯いかがですか？",
    "term_with_transcription": "もう一杯[いっぱ]いかがですか",
    "example_with_transcription": "コーヒーをもう一杯[いっぱ]いかがですか？",
    "audio_word": "https://assets.peatch.io/audio/japanese/word_3tvCkQB0Pk.m4a",
    "audio_example": "https://assets.peatch.io/audio/japanese/example_3I49qEU5hM.m4a"
  },
  {
    "term": "いいえ、けっこうです",
    "frequency": 160,
    "example_en": "No, thank you.",
    "example_ru": "Нет, спасибо.",
    "meaning_en": "No, thank you.",
    "meaning_ru": "Нет, спасибо.",
    "transcription": "いいえ、けっこうです",
    "example_native": "もうお腹がいっぱいです。いいえ、けっこうです。",
    "term_with_transcription": "いいえ、けっこうです",
    "example_with_transcription": "もうお腹[なか]がいっぱいです。いいえ、けっこうです。",
    "audio_word": "https://assets.peatch.io/audio/japanese/word_L8in1Z577j.m4a",
    "audio_example": "https://assets.peatch.io/audio/japanese/example_w5b3FgjhU1.m4a"
  },
  {
    "term": "もう～ですね",
    "frequency": 400,
    "example_en": "It's already ~, isn't it?",
    "example_ru": "Уже ~, не так ли?",
    "meaning_en": "It's already ~, isn't it?",
    "meaning_ru": "Уже ~, не так ли?",
    "transcription": "もう～ですね",
    "example_native": "もう春ですね。",
    "term_with_transcription": "もう～ですね",
    "example_with_transcription": "もう春[はる]ですね。",
    "audio_word": "https://assets.peatch.io/audio/japanese/word_MzC6ZeSXDu.m4a",
    "audio_example": "https://assets.peatch.io/audio/japanese/example_vGCseNbwuA.m4a"
  },
  {
    "term": "そろそろ失礼します",
    "frequency": 450,
    "example_en": "It's almost time to leave now.",
    "example_ru": "Пора уходить.",
    "meaning_en": "It's almost time to leave now.",
    "meaning_ru": "Пора уходить.",
    "transcription": "そろそろしつれいします",
    "example_native": "そろそろ失礼します。",
    "term_with_transcription": "そろそろ失礼[しつれい]します",
    "example_with_transcription": "そろそろ失礼[しつれい]します。",
    "audio_word": "https://assets.peatch.io/audio/japanese/word_r1MlQrI-0t.m4a",
    "audio_example": "https://assets.peatch.io/audio/japanese/example_OthpxDdVc3.m4a"
  },
  {
    "term": "またいらっしゃってください",
    "frequency": 600,
    "example_en": "Please come again.",
    "example_ru": "Пожалуйста, приходите ещё.",
    "meaning_en": "Please come again.",
    "meaning_ru": "Пожалуйста, приходите ещё.",
    "transcription": "またいらっしゃってください",
    "example_native": "またいらっしゃってください。",
    "term_with_transcription": "またいらっしゃってください",
    "example_with_transcription": "またいらっしゃってください。",
    "audio_word": "https://assets.peatch.io/audio/japanese/word_q3HUVCStRA.m4a",
    "audio_example": "https://assets.peatch.io/audio/japanese/example_MMtbVZBSFf.m4a"
  }
]